Primos/Primos.py
Primos_Obertol/Primos_Obertol.py
Primos_Obertol-1.0.dist-info/LICENSE.txt
Primos_Obertol-1.0.dist-info/METADATA
Primos_Obertol-1.0.dist-info/WHEEL
Primos_Obertol-1.0.dist-info/top_level.txt
Primos_Obertol-1.0.dist-info/RECORD
