Metadata-Version: 2.1
Name: Primos-Obertol
Version: 1.0
Summary: Funcion para calcular numeros primos
Home-page: UNKNOWN
Author: Oliver Bertol
Author-email: UNKNOWN
License: GNU
Keywords: primos mathematical operations
Platform: UNKNOWN
Classifier: Development Status :: 4 - Beta
Classifier: Programming Language :: Python :: 3
